[
    {
        "category": "완구용품",
        "uid": "e6727a8c-8a12-4a8d-bc29-1afb70e713e2",
        "name": "타티네쇼콜라 U포미손목딸랑이",
        "brand": "타티네쇼콜라",
        "sale_price": "18,400원",
        "link": "https://i-mom.co.kr/goods/view?no=1703",
        "img": "https://i-mom.co.kr/data/goods/1/2025/01/1703_temp_17362375581035list1.jpg"
    },
    {
        "category": "완구용품",
        "uid": "9c762d4e-43bb-4b2c-b507-ffb5fc6e8c6f",
        "name": "몽슈레 꿀벌 신생아 이불/매트 세트 냄새제거 항균 알러지케어",
        "brand": "몽슈레",
        "sale_price": "96,000원",
        "link": "https://i-mom.co.kr/goods/view?no=1670",
        "img": "https://i-mom.co.kr/data/goods/13/2024/12/1670_temp_17350193400791list1.jpg"
    },
    {
        "category": "완구용품",
        "uid": "f2777c55-43cc-4138-929e-84701f273b12",
        "name": "몽슈레 웨치바이오 냉감베개 커버 어린이용 성인용",
        "brand": "몽슈레",
        "sale_price": "19,100원",
        "link": "https://i-mom.co.kr/goods/view?no=1669",
        "img": "https://i-mom.co.kr/data/goods/13/2024/12/1669_temp_17349311192135list1.jpg"
    },
    {
        "category": "완구용품",
        "uid": "21ae89a5-6335-4284-9cc0-edde7a629d8c",
        "name": "타티네쇼콜라 Augustin_P",
        "brand": "타티네쇼콜라",
        "sale_price": "109,000원",
        "link": "https://i-mom.co.kr/goods/view?no=1659",
        "img": "https://i-mom.co.kr/data/goods/1/2024/12/1659_temp_17338153248910list1.jpg"
    },
    {
        "category": "완구용품",
        "uid": "a16e3417-16c3-4a06-b94f-7b54f22d9b72",
        "name": "몽슈레 리뉴얼 베베룬 달님베개 커버",
        "brand": "몽슈레",
        "sale_price": "16,800원",
        "link": "https://i-mom.co.kr/goods/view?no=1646",
        "img": "https://i-mom.co.kr/data/goods/13/2024/12/1646_temp_17334686845538list1.jpg"
    },
    {
        "category": "완구용품",
        "uid": "96791591-ce19-48e8-8fb7-43ba38ef27e7",
        "name": "몽슈레 태열베개 커버",
        "brand": "몽슈레",
        "sale_price": "9,600원",
        "link": "https://i-mom.co.kr/goods/view?no=1644",
        "img": "https://i-mom.co.kr/data/goods/13/2024/12/1644_temp_17332993892973list1.jpg"
    },
    {
        "category": "완구용품",
        "uid": "c0a1bc67-6d12-4a02-9005-132ba2d49301",
        "name": "몽슈레 꿈에디션 피톤치드 짱구베개",
        "brand": "몽슈레",
        "sale_price": "32,000원",
        "link": "https://i-mom.co.kr/goods/view?no=1643",
        "img": "https://i-mom.co.kr/data/goods/13/2024/12/1643_temp_17332093737798list1.jpg"
    },
    {
        "category": "완구용품",
        "uid": "fd83081f-14f2-4475-bd9c-397599af292b",
        "name": "몽슈레 신생아 태열베개 2단계 대사이즈 (6~24개월)",
        "brand": "몽슈레",
        "sale_price": "95,000원",
        "link": "https://i-mom.co.kr/goods/view?no=1641",
        "img": "https://i-mom.co.kr/data/goods/1/2024/12/1641_2024120210563829.jpg"
    },
    {
        "category": "완구용품",
        "uid": "74250b6a-861a-46cf-9f8f-94c05381c43a",
        "name": "몽슈레 달님 피톤치드 짱구베개",
        "brand": "몽슈레",
        "sale_price": "31,000원",
        "link": "https://i-mom.co.kr/goods/view?no=1292",
        "img": "https://i-mom.co.kr/data/goods/13/2024/11/1292_temp_17313073530182list1.png"
    },
    {
        "category": "완구용품",
        "uid": "a4dc1a2a-ff21-49fc-8798-16886bae77c9",
        "name": "[아이랑] 아띠에어 골드립 힙시트 캐리어",
        "brand": "아이랑",
        "sale_price": "280,000원",
        "link": "https://i-mom.co.kr/goods/view?no=1291",
        "img": "https://i-mom.co.kr/data/goods/1/2024/11/1291_2024110814341624.jpg"
    },
    {
        "category": "완구용품",
        "uid": "24e5b912-7eb7-43fb-9a25-cc6e4198a1b0",
        "name": "몽슈레 pcm 패드",
        "brand": "몽슈레",
        "sale_price": "30,000원",
        "link": "https://i-mom.co.kr/goods/view?no=1289",
        "img": "https://i-mom.co.kr/data/goods/13/2024/11/1289_temp_17310420529558list1.jpg"
    },
    {
        "category": "완구용품",
        "uid": "ff3df51d-d54d-457c-8bb3-eb98e4a9c5ac",
        "name": "몽슈레 안심베개 대사이즈 (24~60개월 태열베개)",
        "brand": "몽슈레",
        "sale_price": "105,000원",
        "link": "https://i-mom.co.kr/goods/view?no=1269",
        "img": "https://i-mom.co.kr/data/goods/13/2024/11/1269_temp_17309611344640list1.jpg"
    },
    {
        "category": "완구용품",
        "uid": "ab158cfe-82f9-4cee-88e4-99e44c43a017",
        "name": "몽슈레 안심베개 (12~26개월 태열베개)",
        "brand": "몽슈레",
        "sale_price": "100,000원",
        "link": "https://i-mom.co.kr/goods/view?no=1209",
        "img": "https://i-mom.co.kr/data/goods/13/2024/11/1209_temp_17308752009280list1.jpg"
    },
    {
        "category": "완구용품",
        "uid": "aaef29e0-1e51-45cf-9737-01d5fbab2d19",
        "name": "[아이랑] 아띠에어 프리 아이보리, 그레이 / EPP폼 소프트쿠션폼",
        "brand": "아이랑",
        "sale_price": "168,000원",
        "link": "https://i-mom.co.kr/goods/view?no=1290",
        "img": "https://i-mom.co.kr/data/goods/1/2024/11/1290_2024110814071429.jpg"
    },
    {
        "category": "완구용품",
        "uid": "d7d73476-1b2d-4cbc-a416-7603422e05da",
        "name": "웅진씽크빅 [교구] 빅지그스 - 아기 활동놀이 센터",
        "brand": "웅진씽크빅",
        "sale_price": "45,000원",
        "link": "https://i-mom.co.kr/goods/view?no=1173",
        "img": "https://i-mom.co.kr/data/goods/10/2024/11/1173_temp_17306847496866list1.jpg"
    },
    {
        "category": "완구용품",
        "uid": "b04fba72-4d62-487e-aa2f-0416472b1b5c",
        "name": "웅진씽크빅 [교구] 빅지그스 - 레인보우 쌓기블럭",
        "brand": "웅진씽크빅",
        "sale_price": "19,900원",
        "link": "https://i-mom.co.kr/goods/view?no=1172",
        "img": "https://i-mom.co.kr/data/goods/10/2024/11/1172_temp_17306846989039list1.jpg"
    },
    {
        "category": "완구용품",
        "uid": "e5d6fdcf-9bc0-4305-944a-20b9f8e4f13b",
        "name": "웅진씽크빅 [교구] 빅지그스 - 모양 분류블럭",
        "brand": "웅진씽크빅",
        "sale_price": "35,000원",
        "link": "https://i-mom.co.kr/goods/view?no=1171",
        "img": "https://i-mom.co.kr/data/goods/10/2024/11/1171_temp_17306846442042list1.jpg"
    },
    {
        "category": "완구용품",
        "uid": "d810c764-233c-4e99-9d44-016bb67c707d",
        "name": "타티네쇼콜라 Augustin_E",
        "brand": "타티네쇼콜라",
        "sale_price": "109,000원",
        "link": "https://i-mom.co.kr/goods/view?no=1658",
        "img": "https://i-mom.co.kr/data/goods/1/2024/12/1658_temp_17338152672213list1.jpg"
    },
    {
        "category": "완구용품",
        "uid": "784fd68c-26fc-48b2-a46e-383d40953f28",
        "name": "웅진씽크빅 [교구] 빅지그스 - 학습놀이 구구단 퍼즐",
        "brand": "웅진씽크빅",
        "sale_price": "27,900원",
        "link": "https://i-mom.co.kr/goods/view?no=1170",
        "img": "https://i-mom.co.kr/data/goods/10/2024/11/1170_temp_17306845829671list1.jpg"
    },
    {
        "category": "완구용품",
        "uid": "a3e97629-11f4-4071-981f-015366b8e0f9",
        "name": "웅진씽크빅 [교구] 빅지그스 - 학습놀이 수배열판",
        "brand": "웅진씽크빅",
        "sale_price": "34,900원",
        "link": "https://i-mom.co.kr/goods/view?no=1169",
        "img": "https://i-mom.co.kr/data/goods/10/2024/11/1169_temp_17306845158289list1.jpg"
    },
    {
        "category": "완구용품",
        "uid": "f43107ec-20c3-449f-8d84-cfd5ed616e24",
        "name": "웅진씽크빅 [교구] 빅지그스 - 동물 끼우기 자동차",
        "brand": "웅진씽크빅",
        "sale_price": "38,900원",
        "link": "https://i-mom.co.kr/goods/view?no=1168",
        "img": "https://i-mom.co.kr/data/goods/10/2024/11/1168_temp_17306844156908list1.jpg"
    },
    {
        "category": "완구용품",
        "uid": "f639f628-f669-4239-8f93-d99a55d583ce",
        "name": "웅진씽크빅 [교구] 빅지그스 - 소근육발달 페그놀이",
        "brand": "웅진씽크빅",
        "sale_price": "33,500원",
        "link": "https://i-mom.co.kr/goods/view?no=1167",
        "img": "https://i-mom.co.kr/data/goods/10/2024/11/1167_temp_17306843594355list1.jpg"
    },
    {
        "category": "완구용품",
        "uid": "91743a49-eede-43df-960b-71b0a7cd1b2b",
        "name": "웅진씽크빅 [교구] 빅지그스 - 학습놀이 분수퍼즐",
        "brand": "웅진씽크빅",
        "sale_price": "38,900원",
        "link": "https://i-mom.co.kr/goods/view?no=1166",
        "img": "https://i-mom.co.kr/data/goods/10/2024/11/1166_temp_17306843126428list1.jpg"
    },
    {
        "category": "완구용품",
        "uid": "c29dc7da-cf8e-492e-b4af-aab5099c911f",
        "name": "웅진씽크빅 [교구] 빅지그스 - 망치 두드르기",
        "brand": "웅진씽크빅",
        "sale_price": "32,900원",
        "link": "https://i-mom.co.kr/goods/view?no=1165",
        "img": "https://i-mom.co.kr/data/goods/10/2024/11/1165_temp_17306842425976list1.jpg"
    },
    {
        "category": "완구용품",
        "uid": "fa1deace-d61f-4418-9b88-e46e61678e77",
        "name": "웅진씽크빅 [교구] 빅지그스 - 탐색놀이 자동차",
        "brand": "웅진씽크빅",
        "sale_price": "36,000원",
        "link": "https://i-mom.co.kr/goods/view?no=1164",
        "img": "https://i-mom.co.kr/data/goods/10/2024/11/1164_temp_17306841359132list1.jpg"
    },
    {
        "category": "완구용품",
        "uid": "83cf81d4-3a27-4e13-827e-8dfeced77adb",
        "name": "웅진씽크빅 [교구] 빅지그스 - 우리 동네 기차(50pcs)",
        "brand": "웅진씽크빅",
        "sale_price": "65,000원",
        "link": "https://i-mom.co.kr/goods/view?no=1163",
        "img": "https://i-mom.co.kr/data/goods/10/2024/11/1163_temp_17306840559150list1.jpg"
    },
    {
        "category": "완구용품",
        "uid": "50093a23-36e6-4f10-bd09-df1193cae0ae",
        "name": "웅진씽크빅 [교구] 빅지그스 - 날씨 밸런스 게임",
        "brand": "웅진씽크빅",
        "sale_price": "20,000원",
        "link": "https://i-mom.co.kr/goods/view?no=1162",
        "img": "https://i-mom.co.kr/data/goods/10/2024/11/1162_temp_17306839994869list1.jpg"
    },
    {
        "category": "완구용품",
        "uid": "e2ff87bb-2fac-4628-9d97-ead8cfb6e65b",
        "name": "웅진씽크빅 [교구] 빅지그스 - 농장 기차(48pcs)",
        "brand": "웅진씽크빅",
        "sale_price": "65,000원",
        "link": "https://i-mom.co.kr/goods/view?no=1161",
        "img": "https://i-mom.co.kr/data/goods/10/2024/11/1161_temp_17306839350988list1.jpg"
    },
    {
        "category": "완구용품",
        "uid": "5bc78952-9588-45dc-8cf2-6eeb75e4ddaf",
        "name": "웅진씽크빅 [교구] 빅지그스 - 모양 매칭 게임",
        "brand": "웅진씽크빅",
        "sale_price": "27,000원",
        "link": "https://i-mom.co.kr/goods/view?no=1160",
        "img": "https://i-mom.co.kr/data/goods/10/2024/11/1160_temp_17306838638278list1.jpg"
    },
    {
        "category": "완구용품",
        "uid": "9f16cf63-cb7f-4d76-a0e5-1c4b78a021ac",
        "name": "웅진씽크빅 [교구] 빅지그스 - 자연 활동 센터",
        "brand": "웅진씽크빅",
        "sale_price": "46,000원",
        "link": "https://i-mom.co.kr/goods/view?no=1159",
        "img": "https://i-mom.co.kr/data/goods/1/2024/11/1159_2024110410273121.jpg"
    },
    {
        "category": "완구용품",
        "uid": "3d0c833c-7aa0-4880-8663-b09727f31cd6",
        "name": "몽슈레 신생아 태열베개 (0~12개월)",
        "brand": "몽슈레",
        "sale_price": "80,000원",
        "link": "https://i-mom.co.kr/goods/view?no=1157",
        "img": "https://i-mom.co.kr/data/goods/13/2024/10/1157_temp_17303624021065list1.jpg"
    },
    {
        "category": "완구용품",
        "uid": "28447ef6-a89a-47cb-a100-aa113884fb3f",
        "name": "몽슈레 웨치바이오 양면 태열베개",
        "brand": "몽슈레",
        "sale_price": "46,800원",
        "link": "https://i-mom.co.kr/goods/view?no=1156",
        "img": "https://i-mom.co.kr/data/goods/13/2024/10/1156_temp_17302699918075list1.jpg"
    },
    {
        "category": "완구용품",
        "uid": "183584f3-b8d4-444c-8506-b59b8649a60a",
        "name": "몽슈레 신생아 베베룬 달님 태열베개 (0~12개월)",
        "brand": "몽슈레",
        "sale_price": "53,900원",
        "link": "https://i-mom.co.kr/goods/view?no=1140",
        "img": "https://i-mom.co.kr/data/goods/13/2024/10/1140_temp_17298328525243list1.jpg"
    },
    {
        "category": "완구용품",
        "uid": "37c3af80-ba29-4fae-bddd-1a5fe8105cf5",
        "name": "몽슈레 넥서포터 (아기병아리/워킹베어/해피캠핑/카키고양이 선택)",
        "brand": "몽슈레",
        "sale_price": "30,000원",
        "link": "https://i-mom.co.kr/goods/view?no=1136",
        "img": "https://i-mom.co.kr/data/goods/13/2024/10/1136_temp_17298303599966list1.jpg"
    },
    {
        "category": "완구용품",
        "uid": "d7c71482-ff52-415e-8618-4469c3bb9427",
        "name": "★우주손전등교구100원★ 잠들기 10분 전 꿈나라 세트 (잠들기10분전 7권+우주손전등)",
        "brand": "우주손전등교구100원",
        "sale_price": "58,600원",
        "link": "https://i-mom.co.kr/goods/view?no=1132",
        "img": "https://i-mom.co.kr/data/goods/10/2024/10/1132_temp_17295572423058list1.jpg"
    },
    {
        "category": "완구용품",
        "uid": "34c07d7d-c220-4d10-8e80-a5fb222d1019",
        "name": "웅진씽크빅 [교구] 빅지그스 - 모양 꼭지퍼즐",
        "brand": "웅진씽크빅",
        "sale_price": "19,900원",
        "link": "https://i-mom.co.kr/goods/view?no=1118",
        "img": "https://i-mom.co.kr/data/goods/10/2024/11/1118_temp_17306837672414list1.jpg"
    },
    {
        "category": "완구용품",
        "uid": "597fd6e9-67fe-4288-8efe-c65200c176ab",
        "name": "웅진씽크빅 [세트] 웅진 베이비 오감튼튼 51종 풀세트 (공룡 텐트포함)",
        "brand": "웅진씽크빅",
        "sale_price": "289,000원",
        "link": "https://i-mom.co.kr/goods/view?no=1117",
        "img": "https://i-mom.co.kr/data/goods/10/2024/10/1117_temp_17278519035482list1.jpg"
    },
    {
        "category": "완구용품",
        "uid": "634ee0f3-5b74-4c51-a00a-25899a44db45",
        "name": "웅진씽크빅 [세트] 좋아!좋아! 웅진 예술놀이 아티비티북",
        "brand": "웅진씽크빅",
        "sale_price": "64,800원",
        "link": "https://i-mom.co.kr/goods/view?no=1116",
        "img": "https://i-mom.co.kr/data/goods/10/2024/10/1116_temp_17278518235093list1.jpg"
    },
    {
        "category": "완구용품",
        "uid": "2ead294e-9670-47ca-bccf-107741bb4865",
        "name": "웅진씽크빅 [세트] 파니의 마음여행 7권 세트",
        "brand": "웅진씽크빅",
        "sale_price": "54,000원",
        "link": "https://i-mom.co.kr/goods/view?no=1115",
        "img": "https://i-mom.co.kr/data/goods/10/2024/10/1115_temp_17278517600526list1.jpg"
    },
    {
        "category": "완구용품",
        "uid": "dec98428-184f-42ae-b881-d2f248077457",
        "name": "웅진씽크빅 [세트]웅진 액티비티 명작그림책 (12권)",
        "brand": "웅진씽크빅",
        "sale_price": "54,000원",
        "link": "https://i-mom.co.kr/goods/view?no=1114",
        "img": "https://i-mom.co.kr/data/goods/10/2024/10/1114_temp_17278516382500list1.jpg"
    },
    {
        "category": "완구용품",
        "uid": "47edb022-419c-4a14-b9dc-7a59f4f03b5f",
        "name": "웅진씽크빅 [세트] 잠들기 10분 전 7권 세트",
        "brand": "웅진씽크빅",
        "sale_price": "58,500원",
        "link": "https://i-mom.co.kr/goods/view?no=1113",
        "img": "https://i-mom.co.kr/data/goods/10/2024/10/1113_temp_17278515502542list1.jpg"
    },
    {
        "category": "완구용품",
        "uid": "9cc83430-0e7e-43aa-8c8d-4125d6832d6e",
        "name": "웅진씽크빅 [세트] 펼치고 세우는 놀이 하우스 4권 세트 입체북",
        "brand": "웅진씽크빅",
        "sale_price": "49,500원",
        "link": "https://i-mom.co.kr/goods/view?no=1112",
        "img": "https://i-mom.co.kr/data/goods/10/2024/10/1112_temp_17278514744494list1.jpg"
    },
    {
        "category": "완구용품",
        "uid": "12425d0b-fefd-4a27-93df-b2daeaae7282",
        "name": "웅진씽크빅 [세트] 웅진 공룡 인성생활동화 내 친구 니노 7권 세트",
        "brand": "웅진씽크빅",
        "sale_price": "50,400원",
        "link": "https://i-mom.co.kr/goods/view?no=1111",
        "img": "https://i-mom.co.kr/data/goods/10/2024/10/1111_temp_17278513955285list1.jpg"
    },
    {
        "category": "완구용품",
        "uid": "56c0b31f-b284-440b-921f-97ffc7feb927",
        "name": "웅진씽크빅 베베북클럽 1단계 (6개월~12개월) Step 4 - 소근육 발달 자극",
        "brand": "웅진씽크빅",
        "sale_price": "39,600원",
        "link": "https://i-mom.co.kr/goods/view?no=1107",
        "img": "https://i-mom.co.kr/data/goods/10/2024/10/1107_temp_17278481483873list1.png"
    },
    {
        "category": "완구용품",
        "uid": "0764cdee-e9d7-4072-bd87-892d520adf0d",
        "name": "웅진씽크빅 베베북클럽 3단계 (18개월~24개월) Step 12 - 수과학 탐구 활동",
        "brand": "웅진씽크빅",
        "sale_price": "39,600원",
        "link": "https://i-mom.co.kr/goods/view?no=1103",
        "img": "https://i-mom.co.kr/data/goods/10/2024/10/1103_temp_17278475881752list1.png"
    },
    {
        "category": "완구용품",
        "uid": "a9170a26-45fa-4a99-a9ac-a519344a0f21",
        "name": "웅진씽크빅 베베북클럽 3단계 (18개월~24개월) Step 11 - 수과학 인지 활동",
        "brand": "웅진씽크빅",
        "sale_price": "39,600원",
        "link": "https://i-mom.co.kr/goods/view?no=1102",
        "img": "https://i-mom.co.kr/data/goods/10/2024/10/1102_temp_17278476114866list1.png"
    },
    {
        "category": "완구용품",
        "uid": "3bff24c4-cf7d-4d8c-814a-121a551c7413",
        "name": "웅진씽크빅 베베북클럽 3단계 (18개월~24개월) Step 10 - 자연과 미술 표현 활동",
        "brand": "웅진씽크빅",
        "sale_price": "39,600원",
        "link": "https://i-mom.co.kr/goods/view?no=1101",
        "img": "https://i-mom.co.kr/data/goods/10/2024/10/1101_temp_17278476284871list1.png"
    },
    {
        "category": "완구용품",
        "uid": "b8ac2cdd-43d9-449a-8175-85dbb103e219",
        "name": "웅진씽크빅 베베북클럽 2단계 (12개월~18개월) Step 8 - 정서 표현 활동",
        "brand": "웅진씽크빅",
        "sale_price": "39,600원",
        "link": "https://i-mom.co.kr/goods/view?no=1099",
        "img": "https://i-mom.co.kr/data/goods/10/2024/10/1099_temp_17278476636177list1.png"
    },
    {
        "category": "완구용품",
        "uid": "9d79c0e3-6304-4556-a392-aca835fd92fc",
        "name": "타티네쇼콜라 Constant the rabbit (110cm) 인형",
        "brand": "타티네쇼콜라",
        "sale_price": "892,500원",
        "link": "https://i-mom.co.kr/goods/view?no=871",
        "img": "https://i-mom.co.kr/data/goods/1/2024/08/871_temp_17230122055192list1.jpg"
    },
    {
        "category": "완구용품",
        "uid": "3c671c6f-180a-4447-b8b0-73a6df05b538",
        "name": "트렁키 프리미엄 영국 유아캐리어 PERCY POLICE CAR",
        "brand": "트렁키",
        "sale_price": "69,900원",
        "link": "https://i-mom.co.kr/goods/view?no=865",
        "img": "https://i-mom.co.kr/data/goods/6/2024/07/865_temp_17218819953064list1.jpg"
    },
    {
        "category": "완구용품",
        "uid": "0989e638-1154-4046-85e5-fe715fc82fee",
        "name": "트렁키 프리미엄 영국 유아캐리어 CANDY CAT",
        "brand": "트렁키",
        "sale_price": "69,900원",
        "link": "https://i-mom.co.kr/goods/view?no=864",
        "img": "https://i-mom.co.kr/data/goods/6/2024/07/864_temp_17218817832701list1.jpg"
    },
    {
        "category": "완구용품",
        "uid": "67a471db-b101-4343-8e98-f3da9d47c2f5",
        "name": "트렁키 프리미엄 영국 아동용캐리어 Bernard the Bee",
        "brand": "트렁키",
        "sale_price": "69,900원",
        "link": "https://i-mom.co.kr/goods/view?no=863",
        "img": "https://i-mom.co.kr/data/goods/6/2024/07/863_temp_17218816299270list1.jpg"
    },
    {
        "category": "완구용품",
        "uid": "9ebf83e5-8dcd-41f4-bc55-66228eb8f843",
        "name": "스마트라이크 유아트램폴린 실내 점핑 가정용 방방이 접이식 3in1",
        "brand": "스마트라이크",
        "sale_price": "159,000원",
        "link": "https://i-mom.co.kr/goods/view?no=862",
        "img": "https://i-mom.co.kr/data/goods/6/2024/07/862_temp_17218695265907list1.jpg"
    },
    {
        "category": "완구용품",
        "uid": "e625d16f-1902-49a4-8cea-72254c70d338",
        "name": "베이비코콜라 2.0 아기비데 베이직 컴포트",
        "brand": "베이비코콜라",
        "sale_price": "19,900원",
        "link": "https://i-mom.co.kr/goods/view?no=859",
        "img": "https://i-mom.co.kr/data/goods/1/2024/07/859_2024072412493228.jpg"
    },
    {
        "category": "완구용품",
        "uid": "0b218c16-7038-4e9c-8387-cbcd297ae463",
        "name": "BERG 유아용 버그카트 고투 GO2 SparX RED",
        "brand": "BERG",
        "sale_price": "109,000원",
        "link": "https://i-mom.co.kr/goods/view?no=856",
        "img": "https://i-mom.co.kr/data/goods/6/2024/07/856_temp_17217861926306list1.jpg"
    },
    {
        "category": "완구용품",
        "uid": "779b7fe6-ee76-4c3c-8ead-14024ae5db11",
        "name": "스킵합 애니멀 유아 귀여운 동물 백팩 아동 가방",
        "brand": "스킵합",
        "sale_price": "26,900원",
        "link": "https://i-mom.co.kr/goods/view?no=855",
        "img": "https://i-mom.co.kr/data/goods/6/2024/07/855_temp_17217819151034list1.jpg"
    },
    {
        "category": "완구용품",
        "uid": "f9502d45-ef92-4dae-abf5-5171d7db8970",
        "name": "스킵합 애니멀 유아 귀여운 동물 미아방지가방",
        "brand": "스킵합",
        "sale_price": "23,900원",
        "link": "https://i-mom.co.kr/goods/view?no=854",
        "img": "https://i-mom.co.kr/data/goods/6/2024/07/854_temp_17217810307212list1.jpg"
    },
    {
        "category": "완구용품",
        "uid": "a7ab6d4b-9db8-49dc-99d6-4a799c3e768e",
        "name": "스킵합 엑티비티센터 3 in 1 멀티 쏘서 303325 아기쏘서 점퍼루 놀이테이블 유아책상",
        "brand": "스킵합",
        "sale_price": "159,000원",
        "link": "https://i-mom.co.kr/goods/view?no=853",
        "img": "https://i-mom.co.kr/data/goods/6/2024/07/853_temp_17217804070348list1.jpg"
    },
    {
        "category": "완구용품",
        "uid": "4b7231bd-ab8c-4f76-bbd9-2f5e975dbb5c",
        "name": "스킵합 유아 물놀이 목욕놀이 목욕장난감 꿀벌 물 채우기 235358",
        "brand": "스킵합",
        "sale_price": "14,900원",
        "link": "https://i-mom.co.kr/goods/view?no=852",
        "img": "https://i-mom.co.kr/data/goods/6/2024/07/852_temp_17217251079163list1.jpg"
    },
    {
        "category": "완구용품",
        "uid": "c9b2c268-b188-401d-ab67-7ef7595ec3d1",
        "name": "플랜토이즈 원목장난감 주방놀이 베이커리 티세트 소꿉놀이 3413",
        "brand": "플랜토이즈",
        "sale_price": "29,900원",
        "link": "https://i-mom.co.kr/goods/view?no=849",
        "img": "https://i-mom.co.kr/data/goods/6/2024/07/849_temp_17216458517111list1.jpg"
    },
    {
        "category": "완구용품",
        "uid": "ffa94ce3-f6e4-4a07-85cb-23033ba93f3d",
        "name": "플랜토이즈 원목장난감 악기놀이 우든드럼 컬러실로폰 아코디언 6404 6405 6413",
        "brand": "플랜토이즈",
        "sale_price": "23,900원",
        "link": "https://i-mom.co.kr/goods/view?no=848",
        "img": "https://i-mom.co.kr/data/goods/6/2024/07/848_temp_17216449243138list1.jpg"
    },
    {
        "category": "완구용품",
        "uid": "6856636a-198e-4aef-a417-2fad4511cc72",
        "name": "플랜토이즈 원목장난감 교육놀이 컬러 도형 맞추기 2403",
        "brand": "플랜토이즈",
        "sale_price": "20,900원",
        "link": "https://i-mom.co.kr/goods/view?no=847",
        "img": "https://i-mom.co.kr/data/goods/6/2024/07/847_temp_17216442310124list1.jpg"
    },
    {
        "category": "완구용품",
        "uid": "956509c9-9e40-46eb-ad19-d9c7f205e03e",
        "name": "플랜토이즈 원목장난감 교육놀이 점자 알파벳 5671",
        "brand": "플랜토이즈",
        "sale_price": "26,900원",
        "link": "https://i-mom.co.kr/goods/view?no=846",
        "img": "https://i-mom.co.kr/data/goods/6/2024/07/846_temp_17216441046524list1.jpg"
    },
    {
        "category": "완구용품",
        "uid": "695b26db-7d75-4935-afc8-749c7cb44d58",
        "name": "플랜토이즈 원목장난감 교육놀이 점자 숫자 5654",
        "brand": "플랜토이즈",
        "sale_price": "15,900원",
        "link": "https://i-mom.co.kr/goods/view?no=845",
        "img": "https://i-mom.co.kr/data/goods/6/2024/07/845_temp_17216438714618list1.jpg"
    },
    {
        "category": "완구용품",
        "uid": "b6a6cc9f-fea2-419a-a2fb-360eba175731",
        "name": "플랜토이즈 원목장난감 교육놀이 무지개 링 쌓기 5124",
        "brand": "플랜토이즈",
        "sale_price": "21,900원",
        "link": "https://i-mom.co.kr/goods/view?no=843",
        "img": "https://i-mom.co.kr/data/goods/6/2024/07/843_temp_17216426554495list1.jpg"
    },
    {
        "category": "완구용품",
        "uid": "9a2fdac7-271c-4172-853a-67c941fecaec",
        "name": "플랜토이즈 우드 블록 원목 장난감 교구 나무기둥 도형 맞추기 5125",
        "brand": "플랜토이즈",
        "sale_price": "25,900원",
        "link": "https://i-mom.co.kr/goods/view?no=842",
        "img": "https://i-mom.co.kr/data/goods/6/2024/07/842_temp_17216424783982list1.jpg"
    },
    {
        "category": "완구용품",
        "uid": "dbf6edc6-1270-4666-810d-0dc8a1f0bd01",
        "name": "플랜토이즈 원목장난감 교육놀이 스마일 공구 키트 5540",
        "brand": "플랜토이즈",
        "sale_price": "29,900원",
        "link": "https://i-mom.co.kr/goods/view?no=841",
        "img": "https://i-mom.co.kr/data/goods/6/2024/07/841_temp_17216423321136list1.jpg"
    },
    {
        "category": "완구용품",
        "uid": "36b48ff6-ef6d-4848-9c22-49b8f82fafc8",
        "name": "플랜토이즈 원목장난감 플레이 미니골프 세트 5683",
        "brand": "플랜토이즈",
        "sale_price": "29,900원",
        "link": "https://i-mom.co.kr/goods/view?no=840",
        "img": "https://i-mom.co.kr/data/goods/6/2024/07/840_temp_17216421292044list1.jpg"
    },
    {
        "category": "완구용품",
        "uid": "9dbd7cd7-a703-4cf1-ac72-275dfa28b585",
        "name": "플랜토이즈 원목장난감 플레이 움직이는 해파리 5278",
        "brand": "플랜토이즈",
        "sale_price": "14,900원",
        "link": "https://i-mom.co.kr/goods/view?no=839",
        "img": "https://i-mom.co.kr/data/goods/6/2024/07/839_temp_17216418733908list1.jpg"
    },
    {
        "category": "완구용품",
        "uid": "fb5a5095-1acd-4823-8b38-cab43f650807",
        "name": "플랜토이즈 원목장난감 플레이 아기자동차 5229",
        "brand": "플랜토이즈",
        "sale_price": "14,900원",
        "link": "https://i-mom.co.kr/goods/view?no=838",
        "img": "https://i-mom.co.kr/data/goods/6/2024/07/838_temp_17216417171601list1.jpg"
    },
    {
        "category": "완구용품",
        "uid": "b62e725e-d498-4b23-93b5-cc64ae728544",
        "name": "플랜토이즈 원목장난감 플레이 동글이 5220",
        "brand": "플랜토이즈",
        "sale_price": "14,900원",
        "link": "https://i-mom.co.kr/goods/view?no=837",
        "img": "https://i-mom.co.kr/data/goods/6/2024/07/837_temp_17216413072304list1.jpg"
    },
    {
        "category": "완구용품",
        "uid": "efdc29e0-3373-4d2c-b6c2-ef319a1b8754",
        "name": "영국 짐플리키즈 유아 목욕놀이 촉감놀이 젤리월드 다이노 팩 5921",
        "brand": "영국",
        "sale_price": "22,900원",
        "link": "https://i-mom.co.kr/goods/view?no=825",
        "img": "https://i-mom.co.kr/data/goods/6/2024/07/825_temp_17212867291720list1.jpg"
    },
    {
        "category": "완구용품",
        "uid": "0daafb89-c185-4582-9192-379d4d3a942b",
        "name": "영국 짐플리키즈 유아 목욕놀이 촉감놀이 젤리월드 판타지 팩 5922",
        "brand": "영국",
        "sale_price": "22,900원",
        "link": "https://i-mom.co.kr/goods/view?no=824",
        "img": "https://i-mom.co.kr/data/goods/6/2024/07/_temp_17212866707658list1.jpg"
    },
    {
        "category": "완구용품",
        "uid": "545b8fee-a0d1-461b-8d15-bb62d5f3f9fb",
        "name": "유키두 뿜뿜 변신 코끼리 분수 물놀이 욕조 장난감 40416",
        "brand": "유키두",
        "sale_price": "49,900원",
        "link": "https://i-mom.co.kr/goods/view?no=820",
        "img": "https://i-mom.co.kr/data/goods/6/2024/07/820_temp_17212844064231list1.jpg"
    },
    {
        "category": "완구용품",
        "uid": "11bc73b9-534b-493f-9cd0-4d79432fe903",
        "name": "영국 짐플리키즈 목욕놀이 유아입욕제 레인보우 메가팩 7076 20입",
        "brand": "영국",
        "sale_price": "21,900원",
        "link": "https://i-mom.co.kr/goods/view?no=819",
        "img": "https://i-mom.co.kr/data/goods/1/2024/07/819_2024071815282828.jpg"
    },
    {
        "category": "완구용품",
        "uid": "cb8af382-a135-4201-8790-4b7ad5d6ec1d",
        "name": "유키두 물먹는 앵무새 친구 물놀이 욕조 장난감 40222",
        "brand": "유키두",
        "sale_price": "20,000원",
        "link": "https://i-mom.co.kr/goods/view?no=815",
        "img": "https://i-mom.co.kr/data/goods/6/2024/07/815_temp_17212062324489list1.jpg"
    },
    {
        "category": "완구용품",
        "uid": "67e141ee-f7ab-45a6-b665-a7a84f25dfcf",
        "name": "유키두 물먹는 쑥쑥 달팽이 물놀이 욕조 장난감 40219",
        "brand": "유키두",
        "sale_price": "20,000원",
        "link": "https://i-mom.co.kr/goods/view?no=814",
        "img": "https://i-mom.co.kr/data/goods/6/2024/07/814_temp_17212057841993list1.jpg"
    },
    {
        "category": "완구용품",
        "uid": "e654bc78-758e-4648-a736-1f8fc2704ee8",
        "name": "유키두 알록달록 물고기 낚시놀이 물놀이 욕조 장난감 40217",
        "brand": "유키두",
        "sale_price": "25,900원",
        "link": "https://i-mom.co.kr/goods/view?no=813",
        "img": "https://i-mom.co.kr/data/goods/6/2024/07/813_temp_17212055930486list1.jpg"
    },
    {
        "category": "완구용품",
        "uid": "18531f7a-a94c-4a40-a8ab-f26ee383cf1e",
        "name": "유키두 빵야빵야 공넣기 물대포 물놀이 욕조 장난감 40215",
        "brand": "유키두",
        "sale_price": "39,900원",
        "link": "https://i-mom.co.kr/goods/view?no=812",
        "img": "https://i-mom.co.kr/data/goods/6/2024/07/812_temp_17212053746460list1.jpg"
    },
    {
        "category": "완구용품",
        "uid": "308b9bb5-2644-4c9f-ae80-04dabfcf8aae",
        "name": "유키두 워터 뿜뿜 코끼리코 바가지 물놀이 욕조 장난감 40205 40206",
        "brand": "유키두",
        "sale_price": "17,000원",
        "link": "https://i-mom.co.kr/goods/view?no=811",
        "img": "https://i-mom.co.kr/data/goods/6/2024/07/811_temp_17212051223855list1.jpg"
    },
    {
        "category": "완구용품",
        "uid": "30a8e8d7-10a0-4e2b-b40f-2031242403f1",
        "name": "유키두 삐용삐용 소방관 프레디 물놀이 욕조 장난감 40204",
        "brand": "유키두",
        "sale_price": "47,000원",
        "link": "https://i-mom.co.kr/goods/view?no=810",
        "img": "https://i-mom.co.kr/data/goods/6/2024/07/810_temp_17212818665713list1.jpg"
    },
    {
        "category": "완구용품",
        "uid": "278140fa-0806-48a0-92cd-f721404456aa",
        "name": "유키두 빙글빙글 왕눈이 실험실 물놀이 욕조 장난감 40203",
        "brand": "유키두",
        "sale_price": "23,000원",
        "link": "https://i-mom.co.kr/goods/view?no=809",
        "img": "https://i-mom.co.kr/data/goods/6/2024/07/809_temp_17212043683282list1.jpg"
    },
    {
        "category": "완구용품",
        "uid": "b522452c-1f52-4081-b7f6-d91645a67803",
        "name": "유키두 빙글빙글 매직 오리 분수 물놀이 욕조 장난감 40164",
        "brand": "유키두",
        "sale_price": "47,000원",
        "link": "https://i-mom.co.kr/goods/view?no=808",
        "img": "https://i-mom.co.kr/data/goods/6/2024/07/808_temp_17212037307196list1.jpg"
    },
    {
        "category": "완구용품",
        "uid": "11ecf0bf-7af2-402a-a727-fc30ae61e50f",
        "name": "유키두 빙글빙글 왕눈이 톱니바퀴 물놀이 장난감 40163",
        "brand": "유키두",
        "sale_price": "15,000원",
        "link": "https://i-mom.co.kr/goods/view?no=807",
        "img": "https://i-mom.co.kr/data/goods/6/2024/07/807_temp_17212031393893list1.jpg"
    },
    {
        "category": "완구용품",
        "uid": "e5f72f8c-c834-4f44-841d-04bcd7af942d",
        "name": "유키두 뿜뿜 고래 잠수함 샤워기 물놀이 욕조 장난감 40142",
        "brand": "유키두",
        "sale_price": "39,000원",
        "link": "https://i-mom.co.kr/goods/view?no=806",
        "img": "https://i-mom.co.kr/data/goods/6/2024/07/806_temp_17212029296036list1.jpg"
    },
    {
        "category": "완구용품",
        "uid": "7debe86c-b6c6-4a89-83df-d37ece22fff7",
        "name": "유키두 빙글빙글 매직 왕눈이 수도꼭지 물놀이 욕조 장난감 40141",
        "brand": "유키두",
        "sale_price": "43,000원",
        "link": "https://i-mom.co.kr/goods/view?no=805",
        "img": "https://i-mom.co.kr/data/goods/6/2024/07/805_temp_17212016494839list1.jpg"
    },
    {
        "category": "완구용품",
        "uid": "1682f7c0-db2d-4019-b553-80e686867843",
        "name": "유키두 빙글빙글 왕눈이 잠수함 샤워기 물놀이 장난감 40139",
        "brand": "유키두",
        "sale_price": "47,000원",
        "link": "https://i-mom.co.kr/goods/view?no=804",
        "img": "https://i-mom.co.kr/data/goods/6/2024/07/804_temp_17212006408791list1.jpg"
    },
    {
        "category": "완구용품",
        "uid": "e1deb80e-8cc0-4881-ae7a-09a9cce5f8c1",
        "name": "유키두 왕눈이 매직 버튼 수도꼭지 물놀이 장난감 40141",
        "brand": "유키두",
        "sale_price": "37,000원",
        "link": "https://i-mom.co.kr/goods/view?no=803",
        "img": "https://i-mom.co.kr/data/goods/6/2024/07/803_temp_17212003034150list1.jpg"
    },
    {
        "category": "완구용품",
        "uid": "e3143765-6426-437a-8ae8-7fe674ccb6f9",
        "name": "유키두 시끌시끌 컵쌓기 분수대 물놀이 장난감 40115",
        "brand": "유키두",
        "sale_price": "47,000원",
        "link": "https://i-mom.co.kr/goods/view?no=802",
        "img": "https://i-mom.co.kr/data/goods/1/2024/07/802_2024071715220424.jpg"
    },
    {
        "category": "완구용품",
        "uid": "cb0391b3-29c0-4f88-a8aa-410e93eaa262",
        "name": "타티네쇼콜라 TC B토미 딸랑이인형",
        "brand": "타티네쇼콜라",
        "sale_price": "21,750원",
        "link": "https://i-mom.co.kr/goods/view?no=801",
        "img": "https://i-mom.co.kr/data/goods/1/2024/07/801_temp_17211833356821list1.jpg"
    },
    {
        "category": "완구용품",
        "uid": "0b0a445f-06df-43d8-a0af-bb191820ed37",
        "name": "타티네쇼콜라 TC U용용이 손목딸랑이",
        "brand": "타티네쇼콜라",
        "sale_price": "21,750원",
        "link": "https://i-mom.co.kr/goods/view?no=800",
        "img": "https://i-mom.co.kr/data/goods/1/2024/07/800_temp_17211832153144list1.jpg"
    },
    {
        "category": "완구용품",
        "uid": "7765ee9f-ecca-4d46-b8b2-35da8eeee994",
        "name": "플랜토이즈 빅토리안 돌하우스 가구(추가상품)",
        "brand": "플랜토이즈",
        "sale_price": "24,900원",
        "link": "https://i-mom.co.kr/goods/view?no=707",
        "img": "https://i-mom.co.kr/data/goods/6/2024/06/_temp_17183549145276list1.jpg"
    },
    {
        "category": "완구용품",
        "uid": "91a77fb9-df27-4b1a-98be-6cba590b9f63",
        "name": "플랜토이즈 빅토리안 돌하우스 7124",
        "brand": "플랜토이즈",
        "sale_price": "309,000원",
        "link": "https://i-mom.co.kr/goods/view?no=706",
        "img": "https://i-mom.co.kr/data/goods/6/2024/06/_temp_17183540817543list1.jpg"
    },
    {
        "category": "완구용품",
        "uid": "4e9f9259-7c90-43b7-a656-582d232023a9",
        "name": "영국 짐플리키즈 목욕놀이 유아입욕제 베스밤",
        "brand": "영국",
        "sale_price": "6,900원",
        "link": "https://i-mom.co.kr/goods/view?no=705",
        "img": "https://i-mom.co.kr/data/goods/6/2024/06/_temp_17183535046032list1.jpg"
    },
    {
        "category": "완구용품",
        "uid": "8ae04de4-6479-4476-999a-c629a68dab82",
        "name": "영국 짐플리키즈 300ml 유아버블클렌저 목욕놀이 버블건 3종 세트",
        "brand": "영국",
        "sale_price": "19,900원",
        "link": "https://i-mom.co.kr/goods/view?no=704",
        "img": "https://i-mom.co.kr/data/goods/6/2024/06/_temp_17183531870491list1.jpg"
    },
    {
        "category": "완구용품",
        "uid": "3b16ce1b-3e08-42d2-8435-f832db33ab0f",
        "name": "유키두 워터 뿜뿜 코끼리 샤워기 민트/핑크 40212 40213",
        "brand": "유키두",
        "sale_price": "35,000원",
        "link": "https://i-mom.co.kr/goods/view?no=703",
        "img": "https://i-mom.co.kr/data/goods/6/2024/06/_temp_17183527007927list1.png"
    },
    {
        "category": "완구용품",
        "uid": "46ee6367-2443-471c-9c5b-b94347bc7751",
        "name": "유키두 엉금엉금 멜로디 달팽이 영유아 아기 배밀이 완구 장난감 40113",
        "brand": "유키두",
        "sale_price": "47,000원",
        "link": "https://i-mom.co.kr/goods/view?no=702",
        "img": "https://i-mom.co.kr/data/goods/6/2024/06/_temp_17183523773676list1.png"
    },
    {
        "category": "완구용품",
        "uid": "6b3ffa14-0363-43f4-9b89-ea66e1c530d9",
        "name": "스웨덴 물놀이 교육완구 아쿠아플레이 마운틴레이크 Mountain Lake 1542",
        "brand": "스웨덴",
        "sale_price": "149,000원",
        "link": "https://i-mom.co.kr/goods/view?no=701",
        "img": "https://i-mom.co.kr/data/goods/6/2024/06/_temp_17183520657139list1.jpg"
    },
    {
        "category": "완구용품",
        "uid": "0ee8dcf7-d051-45b5-b710-bcbe7ad728f3",
        "name": "스웨덴 물놀이 교육완구 아쿠아플레이 락박스 LockBox 1516",
        "brand": "스웨덴",
        "sale_price": "79,900원",
        "link": "https://i-mom.co.kr/goods/view?no=700",
        "img": "https://i-mom.co.kr/data/goods/6/2024/06/_temp_17183511967070list1.jpg"
    },
    {
        "category": "완구용품",
        "uid": "e4ba7014-44a4-4c14-b9a5-34227f88bf20",
        "name": "타티네쇼콜라 U 레옹 인형",
        "brand": "타티네쇼콜라",
        "sale_price": "74,250원",
        "link": "https://i-mom.co.kr/goods/view?no=444",
        "img": "https://i-mom.co.kr/data/goods/1/2024/03/444_temp_17097793670301list1.jpg"
    },
    {
        "category": "완구용품",
        "uid": "86a82cac-5508-4110-93f7-ae3614bf3e62",
        "name": "타티네쇼콜라 G 페르디난도 인형",
        "brand": "타티네쇼콜라",
        "sale_price": "89,250원",
        "link": "https://i-mom.co.kr/goods/view?no=443",
        "img": "https://i-mom.co.kr/data/goods/1/2024/03/443_temp_17097792958128list1.jpg"
    },
    {
        "category": "완구용품",
        "uid": "947ae631-b397-4662-abb9-f8aaad2a872f",
        "name": "타티네쇼콜라 B 페르디난도 인형",
        "brand": "타티네쇼콜라",
        "sale_price": "89,250원",
        "link": "https://i-mom.co.kr/goods/view?no=442",
        "img": "https://i-mom.co.kr/data/goods/1/2024/03/442_temp_17097792314687list1.jpg"
    },
    {
        "category": "완구용품",
        "uid": "caabe282-a88c-4541-8728-970ae65f7672",
        "name": "타티네쇼콜라 코니 옥수수 딸랑이 /임신축하선물/신생아선물",
        "brand": "타티네쇼콜라",
        "sale_price": "45,600원",
        "link": "https://i-mom.co.kr/goods/view?no=441",
        "img": "https://i-mom.co.kr/data/goods/1/2024/03/441_temp_17097791048085list1.jpg"
    },
    {
        "category": "완구용품",
        "uid": "f6ec131f-3a75-4717-aed3-d964011a7d0b",
        "name": "타티네쇼콜라 U콘스탄틴인형",
        "brand": "타티네쇼콜라",
        "sale_price": "239,200원",
        "link": "https://i-mom.co.kr/goods/view?no=403",
        "img": "https://i-mom.co.kr/data/goods/1/2024/03/403_temp_17097794842619list1.jpg"
    },
    {
        "category": "완구용품",
        "uid": "429e626d-6bff-48a5-a419-cd6dd5aedafe",
        "name": "[브라운 정품] BRAUN 브라운 귀적외선 체온계 IRT-6030 필터캡 포함",
        "brand": "브라운",
        "sale_price": "129,000원",
        "link": "https://i-mom.co.kr/goods/view?no=397",
        "img": "https://i-mom.co.kr/data/goods/1/2023/12/397_temp_17031332181858list1.jpg"
    }
]